example_project/__init__.py
example_project/setup.py
example_project/crackhead-api/__init__.py
nightmare-0.3.4.dist-info/METADATA
nightmare-0.3.4.dist-info/WHEEL
nightmare-0.3.4.dist-info/top_level.txt
nightmare-0.3.4.dist-info/RECORD
