Metadata-Version: 2.1
Name: nightmare
Version: 0.3.4
Summary: OFFICIAL API FOR https://crackhead.ml
Home-page: https://crackhead.ml
Author: Team ViewSelect
Author-email: teamviewselect@gmail.com
License: UNKNOWN
Platform: UNKNOWN
Classifier: Programming Language :: Python :: 3
Classifier: License :: OSI Approved :: MIT License
Classifier: Operating System :: OS Independent
Requires-Python: >=3.6
